switchbot_actions/__init__.py
switchbot_actions/action_executor.py
switchbot_actions/action_runner.py
switchbot_actions/app.py
switchbot_actions/cli.py
switchbot_actions/component.py
switchbot_actions/config.py
switchbot_actions/config_loader.py
switchbot_actions/error.py
switchbot_actions/handlers.py
switchbot_actions/logging.py
switchbot_actions/mqtt.py
switchbot_actions/prometheus.py
switchbot_actions/scanner.py
switchbot_actions/signals.py
switchbot_actions/state.py
switchbot_actions/store.py
switchbot_actions/switchbot_factory.py
switchbot_actions/timers.py
switchbot_actions/triggers.py
switchbot_actions-2.3.0.dist-info/licenses/LICENSE
switchbot_actions-2.3.0.dist-info/METADATA
switchbot_actions-2.3.0.dist-info/WHEEL
switchbot_actions-2.3.0.dist-info/entry_points.txt
switchbot_actions-2.3.0.dist-info/top_level.txt
switchbot_actions-2.3.0.dist-info/RECORD
