Metadata-Version: 2.4
Name: switchbot-actions
Version: 2.3.0
Summary: A YAML-based automation engine for SwitchBot BLE devices with a Prometheus exporter.
Author-email: Yoshio HANAWA <y@hnw.jp>
License: MIT
Project-URL: Homepage, https://github.com/hnw/switchbot-actions
Project-URL: Repository, https://github.com/hnw/switchbot-actions
Project-URL: Bug Tracker, https://github.com/hnw/switchbot-actions/issues
Keywords: switchbot,automation,prometheus,ble,home-automation
Classifier: Development Status :: 4 - Beta
Classifier: License :: OSI Approved :: MIT License
Classifier: Operating System :: POSIX :: Linux
Classifier: Operating System :: MacOS
Classifier: Operating System :: Microsoft :: Windows
Classifier: Programming Language :: Python :: 3
Classifier: Programming Language :: Python :: 3.11
Classifier: Programming Language :: Python :: 3.12
Classifier: Programming Language :: Python :: 3.13
Classifier: Topic :: Home Automation
Classifier: Topic :: System :: Monitoring
Classifier: Typing :: Typed
Requires-Python: <4.0,>=3.11
License-File: LICENSE
Requires-Dist: pydantic<3.0.0,>=2.11.7
Requires-Dist: pyswitchbot<2.0.0,>=1.0.0
Requires-Dist: blinker<2.0.0,>=1.9.0
Requires-Dist: prometheus-client<0.24.0,>=0.23.1
Requires-Dist: ruamel-yaml<0.19.0,>=0.18.15
Requires-Dist: httpx<0.29.0,>=0.28.1
Requires-Dist: pytimeparse2<2.0.0,>=1.7.1
Requires-Dist: aiomqtt<3.0.0,>=2.4.0
Requires-Dist: bleak<3.0.0,>=2.1.0
Dynamic: license-file
